django_encrypted_filefield/__init__.py
django_encrypted_filefield/admin.py
django_encrypted_filefield/apps.py
django_encrypted_filefield/checks.py
django_encrypted_filefield/constants.py
django_encrypted_filefield/crypt.py
django_encrypted_filefield/fields.py
django_encrypted_filefield/migrations/__init__.py
django_encrypted_filefield/models.py
django_encrypted_filefield/tests/__init__.py
django_encrypted_filefield/tests/test_constants.py
django_encrypted_filefield/tests/test_crypt.py
django_encrypted_filefield/tests/test_fields.py
django_encrypted_filefield/tests/test_views.py
django_encrypted_filefield/views.py
django_encrypted_filefield-0.3.0.dist-info/LICENSE
django_encrypted_filefield-0.3.0.dist-info/WHEEL
django_encrypted_filefield-0.3.0.dist-info/METADATA
django_encrypted_filefield-0.3.0.dist-info/RECORD
